declaratively.py
declaratively-0.0.2.dist-info/WHEEL
declaratively-0.0.2.dist-info/METADATA
declaratively-0.0.2.dist-info/RECORD
