Metadata-Version: 2.1
Name: declaratively
Version: 0.0.2
Summary: Enforced declarative specification of module-level code objects.
Home-page: https://github.com/glyph/Declaratively
Author: Glyph
Author-email: glyph@twistedmatrix.com
Classifier: License :: OSI Approved :: MIT License
